MANIFEST.in
mrp_repair_data.xml
mrp_repair_demo.yml
mrp_repair_report.xml
mrp_repair_sequence.xml
mrp_repair_view.xml
mrp_repair_workflow.xml
setup.py
./__init__.py
./__openerp__.py
./mrp_repair.py
./report/__init__.py
./report/order.py
./wizard/__init__.py
./wizard/cancel_repair.py
./wizard/make_invoice.py
i18n/ar.po
i18n/bg.po
i18n/bs.po
i18n/ca.po
i18n/cs.po
i18n/da.po
i18n/de.po
i18n/es.po
i18n/es_AR.po
i18n/es_CR.po
i18n/es_EC.po
i18n/es_MX.po
i18n/es_VE.po
i18n/et.po
i18n/fi.po
i18n/fr.po
i18n/hi.po
i18n/hr.po
i18n/hu.po
i18n/id.po
i18n/it.po
i18n/ja.po
i18n/ko.po
i18n/lt.po
i18n/lv.po
i18n/mk.po
i18n/mn.po
i18n/mrp_repair.pot
i18n/nl.po
i18n/nl_BE.po
i18n/pl.po
i18n/pt.po
i18n/pt_BR.po
i18n/ro.po
i18n/ru.po
i18n/sl.po
i18n/sq.po
i18n/sr.po
i18n/sr@latin.po
i18n/sv.po
i18n/tlh.po
i18n/tr.po
i18n/uk.po
i18n/vi.po
i18n/zh_CN.po
i18n/zh_TW.po
images/repair_order.jpeg
openerp_mrp_repair.egg-info/PKG-INFO
openerp_mrp_repair.egg-info/SOURCES.txt
openerp_mrp_repair.egg-info/dependency_links.txt
openerp_mrp_repair.egg-info/requires.txt
openerp_mrp_repair.egg-info/top_level.txt
report/order.rml
security/ir.model.access.csv
security/mrp_repair_security.xml
test/mrp_repair_report.yml
test/test_mrp_repair_afterinv.yml
test/test_mrp_repair_b4inv.yml
test/test_mrp_repair_cancel.yml
test/test_mrp_repair_noneinv.yml
wizard/mrp_repair_cancel_view.xml
wizard/mrp_repair_make_invoice_view.xml